quantnbody/__init__.py
quantnbody/bosonic/BoseHubbard.py
quantnbody/bosonic/__init__.py
quantnbody/bosonic/test_bosons_tools.py
quantnbody/bosonic/tools.py
quantnbody/fermionic/__init__.py
quantnbody/fermionic/class_file.py
quantnbody/fermionic/improved_functions_file.py
quantnbody/fermionic/tools.py
quantnbody-1.1.2.dist-info/LICENSE.txt
quantnbody-1.1.2.dist-info/METADATA
quantnbody-1.1.2.dist-info/WHEEL
quantnbody-1.1.2.dist-info/top_level.txt
quantnbody-1.1.2.dist-info/RECORD
