Metadata-Version: 2.1
Name: quantnbody
Version: 1.1.2
Summary: A python package for quantum chemistry/physics to manipulate many-body operators and wave functions.
Home-page: https://github.com/SYalouz/QuantNBody
Author: Saad Yalouz, Martin Rafael Gulin, Sajathan Sekaran
Author-email: yalouzsaad@gmail.com
Keywords: quantum physics and chemistry,quantum many-body systems,exact diagonalization
Classifier: Programming Language :: Python :: 3
Classifier: License :: OSI Approved :: Apache Software License 
License-File: LICENSE.txt
Requires-Dist: scipy
Requires-Dist: numpy
Requires-Dist: numba
